dfk_commons/__init__.py
dfk_commons/abi_getters.py
dfk_commons/constants.py
dfk_commons/abi/Bazaar.json
dfk_commons/abi/ERC20.json
dfk_commons/abi/ERC721.json
dfk_commons/abi/HeroBridgeUpgradeable.json
dfk_commons/abi/HeroCoreDiamond.json
dfk_commons/abi/HeroRent.json
dfk_commons/abi/HeroSale.json
dfk_commons/abi/MeditationCircle.json
dfk_commons/abi/QuestCoreV3.json
dfk_commons/abi/Summon.json
dfk_commons/abi/UniswapPair.json
dfk_commons/abi/UniswapV2Router02.json
dfk_commons/classes/APIService.py
dfk_commons/classes/Account.py
dfk_commons/classes/DFKLogger.py
dfk_commons/classes/Hero.py
dfk_commons/classes/Order.py
dfk_commons/classes/Quest.py
dfk_commons/classes/RPCProvider.py
dfk_commons/classes/TablesManager.py
dfk_commons/classes/Token.py
dfk_commons/functions/get_account.py
dfk_commons/functions/get_api_service.py
dfk_commons/functions/get_cypher_key.py
dfk_commons/functions/get_dfk_logger.py
dfk_commons/functions/get_rpc_provider.py
dfk_commons/functions/get_tables_manager.py
dfk_commons/functions/utils.py
dfk_commons/functions/dfk/buyHero.py
dfk_commons/functions/dfk/buyToken.py
dfk_commons/functions/dfk/sellHero.py
dfk_commons/functions/dfk/sendHero.py
dfk_commons-1.3.6.dist-info/METADATA
dfk_commons-1.3.6.dist-info/WHEEL
dfk_commons-1.3.6.dist-info/licenses/LICENSE
dfk_commons-1.3.6.dist-info/RECORD
