Metadata-Version: 2.4
Name: dfk_commons
Version: 1.3.6
Summary: A package for dfk common functions
Project-URL: Homepage, https://github.com/pypa/sampleproject
Author-email: jtschuwirth <jtschuwirth@gmail.com>, jeschuwirth <jeschuwirth@gmail.com>
License-File: LICENSE
Classifier: License :: OSI Approved :: MIT License
Classifier: Operating System :: OS Independent
Classifier: Programming Language :: Python :: 3
Requires-Python: >=3.9
Requires-Dist: boto3==1.23.1
Requires-Dist: cryptography==43.0.0
Requires-Dist: requests==2.28.1
Requires-Dist: web3==6.13.0
